schirmshots/README.MD
schirmshots/__init__.py
schirmshots/requirements.txt
schirmshots/thirdparty.json
schirmshots-0.10.dist-info/LICENSE.rst
schirmshots-0.10.dist-info/METADATA
schirmshots-0.10.dist-info/WHEEL
schirmshots-0.10.dist-info/top_level.txt
schirmshots-0.10.dist-info/RECORD
