Metadata-Version: 2.1
Name: schirmshots
Version: 0.10
Summary: records multiple (background) windows using ctypes and ffmpeg - Windows only
Home-page: https://github.com/hansalemaos/schirmshots
Author: Johannes Fischer
Author-email: aulasparticularesdealemaosp@gmail.com
License: MIT
Keywords: screen,recording,background,ffmpeg
Classifier: Development Status :: 4 - Beta
Classifier: Programming Language :: Python :: 3 :: Only
Classifier: Programming Language :: Python :: 3.10
Classifier: Topic :: Software Development :: Libraries :: Python Modules
Classifier: Topic :: Utilities
License-File: LICENSE.rst
Requires-Dist: PoorMansHeadless
Requires-Dist: ctrlchandler
Requires-Dist: ctypes-window-info
Requires-Dist: fast-ctypes-screenshots
Requires-Dist: hackyargparser
Requires-Dist: keyboard
Requires-Dist: kthread-sleep
Requires-Dist: subprocess-alive
Requires-Dist: suicideproc
Requires-Dist: touchtouch
Requires-Dist: vidgear
